<?xml version="1.0" ?><annotation>
	<folder>drink</folder>
	<filename>drink_1.jpg</filename>
	<path>E:\GithubEDrive\RealTimeObjectDetection\Tensorflow\workspace\images\drink_1.jpg</path>
	<source>
		<database>Unknown</database>
	</source>
	<size>
		<width>736</width>
		<height>414</height>
		<depth>3</depth>
	</size>
	<segmented>0</segmented>
	<object>
		<name>drink</name>
		<pose>Unspecified</pose>
		<truncated>0</truncated>
		<difficult>0</difficult>
		<bndbox>
			<xmin>290</xmin>
			<ymin>55</ymin>
			<xmax>375</xmax>
			<ymax>154</ymax>
		</bndbox>
	</object>
</annotation>