<?xml version="1.0" ?><annotation>
	<folder>go</folder>
	<filename>go_12.jpg</filename>
	<path>E:\GithubEDrive\RealTimeObjectDetection\Tensorflow\workspace\images\go_12.jpg</path>
	<source>
		<database>Unknown</database>
	</source>
	<size>
		<width>720</width>
		<height>400</height>
		<depth>3</depth>
	</size>
	<segmented>0</segmented>
	<object>
		<name>go</name>
		<pose>Unspecified</pose>
		<truncated>0</truncated>
		<difficult>0</difficult>
		<bndbox>
			<xmin>292</xmin>
			<ymin>170</ymin>
			<xmax>552</xmax>
			<ymax>255</ymax>
		</bndbox>
	</object>
</annotation>